setup.py
probability_dist_joaoassis/Binomialdistribution.py
probability_dist_joaoassis/Gaussiandistribution.py
probability_dist_joaoassis/Generaldistribution.py
probability_dist_joaoassis/__init__.py
probability_dist_joaoassis.egg-info/PKG-INFO
probability_dist_joaoassis.egg-info/SOURCES.txt
probability_dist_joaoassis.egg-info/dependency_links.txt
probability_dist_joaoassis.egg-info/not-zip-safe
probability_dist_joaoassis.egg-info/top_level.txt