Metadata-Version: 1.0
Name: probability-dist-joaoassis
Version: 0.1
Summary: Gaussian distributions
Home-page: UNKNOWN
Author: Joao Vitor Assis
Author-email: UNKNOWN
License: UNKNOWN
Platform: UNKNOWN
